ausrine/__init__.py
ausrine/ausrine.py
ausrine/chrome.py
ausrine-0.1.0.dist-info/LICENSE
ausrine-0.1.0.dist-info/METADATA
ausrine-0.1.0.dist-info/WHEEL
ausrine-0.1.0.dist-info/top_level.txt
ausrine-0.1.0.dist-info/RECORD
