Metadata-Version: 2.2
Name: ausrine
Version: 0.1.0
Summary: A lightweight Selenium wrapper for web automation
Author-email: Naoyuki Yoshinori <1448309+naoyoshinori@users.noreply.github.com>
License: MIT License
Project-URL: Homepage, https://github.com/naoyoshinori/ausrine
Requires-Python: >=3.10
License-File: LICENSE
Requires-Dist: selenium<5.0.0,>=4.0.0
Provides-Extra: dev
Requires-Dist: pytest>=7.0; extra == "dev"
Requires-Dist: build>=1.0.0; extra == "dev"
Requires-Dist: twine>=4.0.0; extra == "dev"
